ratnumber/__init__.py
ratnumber/rational_numbers.py
ratnumber/utils.py
ratnumbers-0.0.9.dist-info/METADATA
ratnumbers-0.0.9.dist-info/WHEEL
ratnumbers-0.0.9.dist-info/top_level.txt
ratnumbers-0.0.9.dist-info/RECORD
